npu_system/mac_array/bf16_multiplier.v
module bf16_multiplier (
    input wire clk,
    input wire rst_n,
    input wire [15:0] a,  // BF16 input
    input wire [15:0] b,  // BF16 input
    input wire in_valid,  // Input valid signal
    output reg out_valid, // Output valid signal
    output reg [15:0] result  // BF16 output
);

    // BF16 format: 1-bit sign, 8-bit exponent, 7-bit mantissa
    wire a_sign, b_sign;
    wire [7:0] a_exp, b_exp;
    wire [6:0] a_mant, b_mant;
    
    // Special case flags
    wire a_is_zero, b_is_zero;
    wire a_is_inf, b_is_inf;
    wire a_is_nan, b_is_nan;
    
    // Stage 1 registers
    reg stage1_sign;
    reg [8:0] stage1_exp;
    reg [13:0] stage1_mant;
    reg stage1_is_zero;
    reg stage1_is_inf;
    reg stage1_is_nan;
    reg stage1_valid;
    
    // Stage 2 registers
    reg stage2_sign;
    reg [7:0] stage2_exp;
    reg [13:0] stage2_mant_full;
    reg stage2_is_zero;
    reg stage2_is_inf;
    reg stage2_is_nan;
    reg stage2_valid;

    // For normalization (Verilog-2001 compatible)
    integer shift;
    
    // Extract components
    assign a_sign = a[15];
    assign b_sign = b[15];
    assign a_exp = a[14:7];
    assign b_exp = b[14:7];
    assign a_mant = a[6:0];
    assign b_mant = b[6:0];
    
    // Check special cases
    assign a_is_zero = (a_exp == 8'd0) && (a_mant == 7'd0);
    assign b_is_zero = (b_exp == 8'd0) && (b_mant == 7'd0);
    assign a_is_inf = (a_exp == 8'hFF) && (a_mant == 7'd0);
    assign b_is_inf = (b_exp == 8'hFF) && (b_mant == 7'd0);
    assign a_is_nan = (a_exp == 8'hFF) && (a_mant != 7'd0);
    assign b_is_nan = (b_exp == 8'hFF) && (b_mant != 7'd0);
    
    // Stage 1: Basic multiplication and exponent calculation
    always @(posedge clk or negedge rst_n) begin
        if (!rst_n) begin
            stage1_sign <= 1'b0;
            stage1_exp <= 9'd0;
            stage1_mant <= 14'd0;
            stage1_is_zero <= 1'b0;
            stage1_is_inf <= 1'b0;
            stage1_is_nan <= 1'b0;
            stage1_valid <= 1'b0;
        end else begin
            stage1_valid <= in_valid;
            if (in_valid) begin
                // Sign calculation
                stage1_sign <= a[15] ^ b[15];
                
                // Special cases
                if (a_is_nan || b_is_nan) begin
                    stage1_is_nan <= 1'b1;
                    stage1_is_zero <= 1'b0;
                    stage1_is_inf <= 1'b0;
                    stage1_exp <= 9'd0;
                    stage1_mant <= 14'd0;
                end else if (a_is_inf || b_is_inf) begin
                    if (a_is_zero || b_is_zero) begin
                        stage1_is_nan <= 1'b1;
                        stage1_is_zero <= 1'b0;
                        stage1_is_inf <= 1'b0;
                    end else begin
                        stage1_is_inf <= 1'b1;
                        stage1_is_zero <= 1'b0;
                        stage1_is_nan <= 1'b0;
                    end
                    stage1_exp <= 9'd0;
                    stage1_mant <= 14'd0;
                end else if (a_is_zero || b_is_zero) begin
                    stage1_is_zero <= 1'b1;
                    stage1_is_inf <= 1'b0;
                    stage1_is_nan <= 1'b0;
                    stage1_exp <= 9'd0;
                    stage1_mant <= 14'd0;
                end else begin
                    stage1_is_zero <= 1'b0;
                    stage1_is_inf <= 1'b0;
                    stage1_is_nan <= 1'b0;
                    
                    // Multiply mantissas first
                    stage1_mant <= {1'b1, a_mant} * {1'b1, b_mant};
                    
                    // Calculate exponent
                    if (a_exp == 0 && b_exp == 0) begin
                        // Both inputs are denormalized
                        stage1_exp <= 9'd0;
                    end else if (a_exp == 0) begin
                        stage1_exp <= {1'b0, b_exp} - 9'd127;
                    end else if (b_exp == 0) begin
                        stage1_exp <= {1'b0, a_exp} - 9'd127;
                    end else begin
                        stage1_exp <= {1'b0, a_exp} + {1'b0, b_exp} - 9'd127;
                    end
                end
            end
        end
    end

    // Stage 2: Normalization and overflow/underflow check
    always @(posedge clk or negedge rst_n) begin
        if (!rst_n) begin
            stage2_sign <= 1'b0;
            stage2_exp <= 8'd0;
            stage2_mant_full <= 14'd0;
            stage2_is_zero <= 1'b0;
            stage2_is_inf <= 1'b0;
            stage2_is_nan <= 1'b0;
            stage2_valid <= 1'b0;
        end else begin
            stage2_valid <= stage1_valid;
            stage2_sign <= stage1_sign;
            stage2_is_nan <= stage1_is_nan;
            if (stage1_is_nan) begin
                stage2_exp <= 8'hFF;
                stage2_mant_full <= 14'h2000;
                stage2_is_zero <= 1'b0;
                stage2_is_inf <= 1'b0;
            end else if (stage1_is_inf) begin
                stage2_exp <= 8'hFF;
                stage2_mant_full <= 14'd0;
                stage2_is_zero <= 1'b0;
                stage2_is_inf <= 1'b1;
            end else if (stage1_is_zero || stage1_mant == 0) begin
                stage2_exp <= 8'd0;
                stage2_mant_full <= 14'd0;
                stage2_is_zero <= 1'b1;
                stage2_is_inf <= 1'b0;
            end else begin
                // Normalize mantissa
                reg [13:0] norm_mant;
                reg [8:0] norm_exp;
                norm_mant = stage1_mant;
                norm_exp = stage1_exp;
                
                // Normalize based on the most significant bit
                if (norm_mant[13]) begin
                    norm_mant = norm_mant >> 1;
                    norm_exp = norm_exp + 1;
                end
                
                // Overflow check (BF16 max exponent is 127)
                if (norm_exp >= 9'd128) begin
                    stage2_exp <= 8'hFF;
                    stage2_mant_full <= 14'd0;
                    stage2_is_inf <= 1'b1;
                    stage2_is_zero <= 1'b0;
                end
                // Underflow
                else if (norm_exp == 0) begin
                    stage2_exp <= 8'd0;
                    stage2_mant_full <= 14'd0;
                    stage2_is_zero <= 1'b1;
                    stage2_is_inf <= 1'b0;
                end else begin
                    stage2_exp <= norm_exp[7:0];
                    stage2_mant_full <= norm_mant;
                    stage2_is_zero <= 1'b0;
                    stage2_is_inf <= 1'b0;
                end
            end
        end
    end

    // Output assignment
    always @(posedge clk or negedge rst_n) begin
        if (!rst_n) begin
            result <= 16'd0;
            out_valid <= 1'b0;
        end else begin
            out_valid <= stage2_valid;
            if (stage2_is_nan) begin
                result <= {1'b0, 8'hFF, 7'h40};  // Quiet NaN
            end else if (stage2_is_inf) begin
                result <= {stage2_sign, 8'hFF, 7'h00};  // Infinity
            end else if (stage2_is_zero) begin
                result <= {stage2_sign, 8'h00, 7'h00};  // Zero
            end else begin
                result <= {stage2_sign, stage2_exp, stage2_mant_full[12:6]};
            end
        end
    end

endmodule

npu_system/mac_array_sim/bf16_multiplier_tb.sv
`timescale 1ns/1ps

// BF16 multiplier testbench using limited SystemVerilog features
module bf16_multiplier_tb;
    // Clock and reset
    logic clk;
    logic rst_n;
    
    // Test vectors
    logic [15:0] a;
    logic [15:0] b;
    logic [15:0] result;
    logic in_valid;
    logic out_valid;
    
    // Expected results
    logic [15:0] expected_result;
    
    // Test statistics
    int total_tests;
    int passed_tests;
    int failed_tests;
    
    // Test category counters
    int normal_passed;
    int normal_total;
    int special_passed;
    int special_total;
    int edge_passed;
    int edge_total;
    
    // Pipeline tracking
    logic [15:0] pipeline_a[0:2];
    logic [15:0] pipeline_b[0:2];
    logic [15:0] pipeline_result[0:2];
    
    // Instantiate BF16 multiplier
    bf16_multiplier dut (
        .clk(clk),
        .rst_n(rst_n),
        .a(a),
        .b(b),
        .in_valid(in_valid),
        .out_valid(out_valid),
        .result(result)
    );
    
    // Clock generation
    initial begin
        clk = 0;
        forever #5 clk = ~clk;  // 100MHz clock
    end
    
    // VCD file generation
    initial begin
        $dumpfile("dump.vcd");
        $dumpvars(0, bf16_multiplier_tb);
        $dumpvars(0, bf16_multiplier_tb.in_valid);
        $dumpvars(0, bf16_multiplier_tb.out_valid);
        $dumpvars(0, bf16_multiplier_tb.dut.in_valid);
        $dumpvars(0, bf16_multiplier_tb.dut.out_valid);
    end
    
    // Run test case
    task run_test_case;
        input [15:0] test_a;
        input [15:0] test_b;
        input [15:0] expected;
        input [1:0] category;  // 0: normal, 1: special, 2: edge
        
        $display("\nRunning test case: A=%h, B=%h", test_a, test_b);
        @(negedge clk); // Change signals at negedge
        a = test_a;
        b = test_b;
        expected_result = expected;
        in_valid = 1'b1;
        
        // Update pipeline tracking
        pipeline_a[0] = a;
        pipeline_b[0] = b;
        
        // Wait for pipeline (3 cycles for the actual implementation)
        repeat(3) @(posedge clk);
        @(negedge clk); // Deassert in_valid at negedge
        in_valid = 1'b0;
        
        // Wait for 10 clock cycles before next test
        repeat(10) @(posedge clk);
        
        // Update category counters before checking result
        case (category)
            2'b00: normal_total++;
            2'b01: special_total++;
            2'b10: edge_total++;
        endcase
        
        // Check result
        if (result === expected_result) begin
            $display("PASSED: A=%h, B=%h", a, b);
            $display("  Time: %t", $time);
            passed_tests++;
            
            // Update category counters
            case (category)
                2'b00: normal_passed++;
                2'b01: special_passed++;
                2'b10: edge_passed++;
            endcase
        end else begin
            $display("FAILED: A=%h, B=%h", a, b);
            $display("  Time: %t", $time);
            $display("  Input A: %h", a);
            $display("  Input B: %h", b);
            $display("  Expected: %h", expected_result);
            $display("  Got: %h", result);
            failed_tests++;
        end
        total_tests++;
    endtask
    
    // Initialize test cases
    task init_test_cases;
        // Normal test cases
        run_test_case(16'h3F80, 16'h4000, 16'h4000, 2'b00);  // 1.0 * 2.0
        run_test_case(16'hBF80, 16'h4000, 16'hC000, 2'b00);  // -1.0 * 2.0
        run_test_case(16'h3F00, 16'h3F00, 16'h3E80, 2'b00);  // 0.5 * 0.5
        
        // Special cases
        run_test_case(16'h0000, 16'h3F80, 16'h0000, 2'b01);  // 0.0 * 1.0
        run_test_case(16'h7F80, 16'h3F80, 16'h7F80, 2'b01);  // inf * 1.0
        run_test_case(16'h7FC0, 16'h3F80, 16'h7FC0, 2'b01);  // NaN * 1.0
        
        // Edge cases
        run_test_case(16'h7F00, 16'h7F00, 16'h7F80, 2'b10);  // 1e38 * 1e38
        run_test_case(16'h0080, 16'h0080, 16'h0000, 2'b10);  // 1e-38 * 1e-38
        run_test_case(16'h0000, 16'h7F80, 16'h7FC0, 2'b10);  // 0 * inf
    endtask
    
    // Run random tests
    task run_random_tests;
        input int num_tests;
        int i;
        reg [31:0] rand_val;
        
        $display("\nRunning %0d random tests", num_tests);
        
        for (i = 0; i < num_tests; i++) begin
            // Generate random inputs using $random
            rand_val = $random;
            a = rand_val[15:0];
            rand_val = $random;
            b = rand_val[15:0];
            
            // Calculate expected result
            expected_result = calculate_bf16_multiply(a, b);
            
            // Update pipeline tracking
            pipeline_a[0] = a;
            pipeline_b[0] = b;
            
            // Wait for pipeline (3 cycles for the actual implementation)
            repeat(3) @(posedge clk);
            
            // Update counters before checking result
            normal_total++;
            
            // Check result
            if (result === expected_result) begin
                passed_tests++;
                normal_passed++;
            end else begin
                $display("Random test %0d failed:", i);
                $display("  Time: %t", $time);
                $display("  Input A: %h", a);
                $display("  Input B: %h", b);
                $display("  Expected: %h", expected_result);
                $display("  Got: %h", result);
                failed_tests++;
            end
            total_tests++;
        end
    endtask
    
    // Pipeline test
    task run_pipeline_test;
        $display("\n=== Running Pipeline Test ===");
        a = 16'h3F80; // 1.0
        b = 16'h4000; // 2.0
        in_valid = 1'b1;
        repeat(3) @(posedge clk);
        in_valid = 1'b0;
        repeat(10) @(posedge clk);
        if (result === 16'h4000) begin
            $display("Pipeline Test PASSED");
        end else begin
            $display("Pipeline Test FAILED");
        end
    endtask
    
    // Main test sequence
    initial begin
        // Initialize
        rst_n = 0;
        a = 16'h0000;
        b = 16'h0000;
        total_tests = 0;
        passed_tests = 0;
        failed_tests = 0;
        normal_passed = 0;
        normal_total = 0;
        special_passed = 0;
        special_total = 0;
        edge_passed = 0;
        edge_total = 0;
        in_valid = 0; // Set initial value of in_valid to 0
        
        // Release reset
        repeat(4) @(posedge clk);
        rst_n = 1;
        repeat(2) @(posedge clk);
        
        // Run basic test cases
        $display("\n=== Running Basic Tests ===");
        init_test_cases();
        
        // Print basic test results
        $display("\n=== Basic Test Results ===");
        $display("Normal Tests: %0d/%0d passed", normal_passed, normal_total);
        $display("Special Tests: %0d/%0d passed", special_passed, special_total);
        $display("Edge Tests: %0d/%0d passed", edge_passed, edge_total);
        
        // Check if basic tests passed
        if (normal_passed == normal_total && 
            special_passed == special_total && 
            edge_passed == edge_total) begin
            // Run pipeline test
            run_pipeline_test();
            // Run random tests only if all basic tests passed
            $display("\n=== Running Random Tests ===");
            run_random_tests(500);
        end else begin
            $display("\n=== Skipping Random Tests - Basic Tests Failed ===");
        end
        
        // Print final test summary
        $display("\n=== Final Test Summary ===");
        $display("Basic Tests:");
        $display("  Normal Tests: %0d/%0d passed", normal_passed, normal_total);
        $display("  Special Tests: %0d/%0d passed", special_passed, special_total);
        $display("  Edge Tests: %0d/%0d passed", edge_passed, edge_total);
        $display("Total Tests: %0d", total_tests);
        $display("Total Passed: %0d", passed_tests);
        $display("Total Failed: %0d", failed_tests);
        
        // End simulation
        #100;
        $finish;
    end
    
    // Function to calculate BF16 multiplication
    function [15:0] calculate_bf16_multiply;
        input [15:0] a, b;
        logic a_sign, b_sign;
        logic [7:0] a_exp, b_exp;
        logic [6:0] a_mant, b_mant;
        logic result_sign;
        logic [7:0] result_exp;
        logic [6:0] result_mant;
        logic [13:0] mult_result;
        
        // Extract components
        a_sign = a[15];
        b_sign = b[15];
        a_exp = a[14:7];
        b_exp = b[14:7];
        a_mant = a[6:0];
        b_mant = b[6:0];
        
        // Handle special cases
        if (a_exp == 8'hFF || b_exp == 8'hFF) begin
            if (a_mant != 0 || b_mant != 0) begin
                // NaN
                calculate_bf16_multiply = {1'b0, 8'hFF, 7'h40};
            end else if ((a_exp == 8'hFF && b_mant == 0) || 
                       (b_exp == 8'hFF && a_mant == 0)) begin
                // Infinity
                calculate_bf16_multiply = {a_sign ^ b_sign, 8'hFF, 7'h00};
            end else begin
                // 0 * inf = NaN
                calculate_bf16_multiply = {1'b0, 8'hFF, 7'h40};
            end
        end else if (a_exp == 0 || b_exp == 0) begin
            // Zero
            calculate_bf16_multiply = {a_sign ^ b_sign, 8'h00, 7'h00};
        end else begin
            // Normal multiplication
            result_sign = a_sign ^ b_sign;
            result_exp = a_exp + b_exp - 8'd127;
            mult_result = {1'b1, a_mant} * {1'b1, b_mant};
            
            // Normalize
            if (mult_result[13]) begin
                result_exp = result_exp + 1;
                result_mant = mult_result[13:7];
            end else begin
                result_mant = mult_result[12:6];
            end
            
            // Check for overflow/underflow
            if (result_exp[7] && !result_exp[6]) begin
                // Underflow
                calculate_bf16_multiply = {result_sign, 8'h00, 7'h00};
            end else if (!result_exp[7] && result_exp[6]) begin
                // Overflow
                calculate_bf16_multiply = {result_sign, 8'hFF, 7'h00};
            end else begin
                calculate_bf16_multiply = {result_sign, result_exp, result_mant};
            end
        end
    endfunction
    
    // Monitor
    initial begin
        $monitor("Time=%0t rst_n=%b a=%h b=%h result=%h",
                 $time, rst_n, a, b, result);
    end

endmodule

npu_system/mac_array_sim/dump.vcd
$date
	Tue Jun  3 14:20:36 2025
$end
$version
	Icarus Verilog
$end
$timescale
	1ps
$end
$scope module bf16_multiplier_tb $end
$var wire 16 ! result [15:0] $end
$var wire 1 " out_valid $end
$var reg 16 # a [15:0] $end
$var reg 16 $ b [15:0] $end
$var reg 1 % clk $end
$var reg 16 & expected_result [15:0] $end
$var reg 1 ' in_valid $end
$var reg 1 ( rst_n $end
$var integer 32 ) edge_passed [31:0] $end
$var integer 32 * edge_total [31:0] $end
$var integer 32 + failed_tests [31:0] $end
$var integer 32 , normal_passed [31:0] $end
$var integer 32 - normal_total [31:0] $end
$var integer 32 . passed_tests [31:0] $end
$var integer 32 / special_passed [31:0] $end
$var integer 32 0 special_total [31:0] $end
$var integer 32 1 total_tests [31:0] $end
$scope function calculate_bf16_multiply $end
$var reg 16 2 a [15:0] $end
$var reg 8 3 a_exp [7:0] $end
$var reg 7 4 a_mant [6:0] $end
$var reg 1 5 a_sign $end
$var reg 16 6 b [15:0] $end
$var reg 8 7 b_exp [7:0] $end
$var reg 7 8 b_mant [6:0] $end
$var reg 1 9 b_sign $end
$var reg 14 : mult_result [13:0] $end
$var reg 8 ; result_exp [7:0] $end
$var reg 7 < result_mant [6:0] $end
$var reg 1 = result_sign $end
$upscope $end
$scope module dut $end
$var wire 16 > a [15:0] $end
$var wire 1 ? a_is_inf $end
$var wire 1 @ a_is_nan $end
$var wire 1 A a_is_zero $end
$var wire 16 B b [15:0] $end
$var wire 1 C b_is_inf $end
$var wire 1 D b_is_nan $end
$var wire 1 E b_is_zero $end
$var wire 1 % clk $end
$var wire 1 ' in_valid $end
$var wire 1 ( rst_n $end
$var wire 1 F b_sign $end
$var wire 7 G b_mant [6:0] $end
$var wire 8 H b_exp [7:0] $end
$var wire 1 I a_sign $end
$var wire 7 J a_mant [6:0] $end
$var wire 8 K a_exp [7:0] $end
$var reg 1 " out_valid $end
$var reg 16 L result [15:0] $end
$var reg 9 M stage1_exp [8:0] $end
$var reg 1 N stage1_is_inf $end
$var reg 1 O stage1_is_nan $end
$var reg 1 P stage1_is_zero $end
$var reg 14 Q stage1_mant [13:0] $end
$var reg 1 R stage1_sign $end
$var reg 1 S stage1_valid $end
$var reg 8 T stage2_exp [7:0] $end
$var reg 1 U stage2_is_inf $end
$var reg 1 V stage2_is_nan $end
$var reg 1 W stage2_is_zero $end
$var reg 14 X stage2_mant_full [13:0] $end
$var reg 1 Y stage2_sign $end
$var reg 1 Z stage2_valid $end
$scope begin $unm_blk_45 $end
$var reg 9 [ norm_exp [8:0] $end
$var reg 14 \ norm_mant [13:0] $end
$upscope $end
$upscope $end
$scope task init_test_cases $end
$upscope $end
$scope task run_pipeline_test $end
$upscope $end
$scope task run_random_tests $end
$var reg 32 ] rand_val [31:0] $end
$var integer 32 ^ i [31:0] $end
$var integer 32 _ num_tests [31:0] $end
$upscope $end
$scope task run_test_case $end
$var reg 2 ` category [1:0] $end
$var reg 16 a expected [15:0] $end
$var reg 16 b test_a [15:0] $end
$var reg 16 c test_b [15:0] $end
$upscope $end
$upscope $end
$enddefinitions $end
$comment Show the parameter values. $end
$dumpall
$end
#0
$dumpvars
bx c
bx b
bx a
bx `
b0 _
b0 ^
bx ]
bx \
bx [
0Z
0Y
b0 X
0W
0V
0U
b0 T
0S
0R
b0 Q
0P
0O
0N
b0 M
b0 L
b0 K
b0 J
0I
b0 H
b0 G
0F
1E
0D
0C
b0 B
1A
0@
0?
b0 >
x=
bx <
bx ;
bx :
x9
bx 8
bx 7
bx 6
x5
bx 4
bx 3
bx 2
b0 1
b0 0
b0 /
b0 .
b0 -
b0 ,
b0 +
b0 *
b0 )
0(
0'
bx &
0%
b0 $
b0 #
0"
b0 !
$end
#5000
1%
#10000
0%
#15000
1%
#20000
0%
#25000
1%
#30000
0%
#35000
1W
1(
1%
#40000
0%
#45000
1%
#50000
0%
#55000
b0 `
b100000000000000 a
b100000000000000 c
b11111110000000 b
1%
#60000
0E
0A
b10000000 H
b1111111 K
1'
b100000000000000 &
b100000000000000 $
b100000000000000 B
b11111110000000 #
b11111110000000 >
0%
#65000
b10000000 M
1S
1%
#70000
0%
#75000
1Z
1%
#80000
0%
#85000
1"
1%
#90000
0'
0%
#95000
0S
1%
#100000
0%
#105000
0Z
1%
#110000
0%
#115000
0"
1%
#120000
0%
#125000
1%
#130000
0%
#135000
1%
#140000
0%
#145000
1%
#150000
0%
#155000
1%
#160000
0%
#165000
1%
#170000
0%
#175000
1%
#180000
0%
#185000
b1100000000000000 a
b1011111110000000 b
b1 1
b1 +
b1 -
1%
#190000
1I
1'
b1100000000000000 &
b1011111110000000 #
b1011111110000000 >
0%
#195000
1R
1S
1%
#200000
0%
#205000
1Y
1Z
1%
#210000
0%
#215000
b1000000000000000 !
b1000000000000000 L
1"
1%
#220000
0'
0%
#225000
0S
1%
#230000
0%
#235000
0Z
1%
#240000
0%
#245000
0"
1%
#250000
0%
#255000
1%
#260000
0%
#265000
1%
#270000
0%
#275000
1%
#280000
0%
#285000
1%
#290000
0%
#295000
1%
#300000
0%
#305000
1%
#310000
0%
#315000
b11111010000000 a
b11111100000000 c
b11111100000000 b
b10 1
b10 +
b10 -
1%
#320000
b1111110 H
0I
b1111110 K
1'
b11111010000000 &
b11111100000000 $
b11111100000000 B
b11111100000000 #
b11111100000000 >
0%
#325000
b1111101 M
0R
1S
1%
#330000
0%
#335000
0Y
1Z
1%
#340000
0%
#345000
b0 !
b0 L
1"
1%
#350000
0'
0%
#355000
0S
1%
#360000
0%
#365000
0Z
1%
#370000
0%
#375000
0"
1%
#380000
0%
#385000
1%
#390000
0%
#395000
1%
#400000
0%
#405000
1%
#410000
0%
#415000
1%
#420000
0%
#425000
1%
#430000
0%
#435000
1%
#440000
0%
#445000
b1 `
b0 a
b11111110000000 c
b0 b
b11 1
b11 +
b11 -
1%
#450000
1A
b1111111 H
b0 K
1'
b0 &
b11111110000000 $
b11111110000000 B
b0 #
b0 >
0%
#455000
b0 M
1P
1S
1%
#460000
0%
#465000
1Z
1%
#470000
0%
#475000
1"
1%
#480000
0'
0%
#485000
0S
1%
#490000
0%
#495000
0Z
1%
#500000
0%
#505000
0"
1%
#510000
0%
#515000
1%
#520000
0%
#525000
1%
#530000
0%
#535000
1%
#540000
0%
#545000
1%
#550000
0%
#555000
1%
#560000
0%
#565000
1%
#570000
0%
#575000
b111111110000000 a
b111111110000000 b
b100 1
b1 /
b1 .
b1 0
1%
#580000
0A
1?
b11111111 K
1'
b111111110000000 &
b111111110000000 #
b111111110000000 >
0%
#585000
0P
1N
1S
1%
#590000
0%
#595000
1U
0W
b11111111 T
1Z
1%
#600000
0%
#605000
b111111110000000 !
b111111110000000 L
1"
1%
#610000
0'
0%
#615000
0S
1%
#620000
0%
#625000
0Z
1%
#630000
0%
#635000
0"
1%
#640000
0%
#645000
1%
#650000
0%
#655000
1%
#660000
0%
#665000
1%
#670000
0%
#675000
1%
#680000
0%
#685000
1%
#690000
0%
#695000
1%
#700000
0%
#705000
b111111111000000 a
b111111111000000 b
b101 1
b10 /
b10 .
b10 0
1%
#710000
0?
1@
b1000000 J
1'
b111111111000000 &
b111111111000000 #
b111111111000000 >
0%
#715000
0N
1O
1S
1%
#720000
0%
#725000
0U
b10000000000000 X
1V
1Z
1%
#730000
0%
#735000
b111111111000000 !
b111111111000000 L
1"
1%
#740000
0'
0%
#745000
0S
1%
#750000
0%
#755000
0Z
1%
#760000
0%
#765000
0"
1%
#770000
0%
#775000
1%
#780000
0%
#785000
1%
#790000
0%
#795000
1%
#800000
0%
#805000
1%
#810000
0%
#815000
1%
#820000
0%
#825000
1%
#830000
0%
#835000
b10 `
b111111110000000 a
b111111100000000 c
b111111100000000 b
b110 1
b11 /
b11 .
b11 0
1%
#840000
0@
b11111110 H
b11111110 K
b0 J
1'
b111111110000000 &
b111111100000000 $
b111111100000000 B
b111111100000000 #
b111111100000000 >
0%
#845000
b101111101 M
0O
1S
1%
#850000
0%
#855000
1W
b0 X
b0 T
0V
1Z
1%
#860000
0%
#865000
b0 !
b0 L
1"
1%
#870000
0'
0%
#875000
0S
1%
#880000
0%
#885000
0Z
1%
#890000
0%
#895000
0"
1%
#900000
0%
#905000
1%
#910000
0%
#915000
1%
#920000
0%
#925000
1%
#930000
0%
#935000
1%
#940000
0%
#945000
1%
#950000
0%
#955000
1%
#960000
0%
#965000
b0 a
b10000000 c
b10000000 b
b111 1
b100 +
b1 *
1%
#970000
b1 H
b1 K
1'
b0 &
b10000000 $
b10000000 B
b10000000 #
b10000000 >
0%
#975000
b110000011 M
1S
1%
#980000
0%
#985000
1Z
1%
#990000
0%
#995000
1"
1%
#1000000
0'
0%
#1005000
0S
1%
#1010000
0%
#1015000
0Z
1%
#1020000
0%
#1025000
0"
1%
#1030000
0%
#1035000
1%
#1040000
0%
#1045000
1%
#1050000
0%
#1055000
1%
#1060000
0%
#1065000
1%
#1070000
0%
#1075000
1%
#1080000
0%
#1085000
1%
#1090000
0%
#1095000
b111111111000000 a
b111111110000000 c
b0 b
b1000 1
b1 )
b100 .
b10 *
1%
#1100000
1C
1A
b11111111 H
b0 K
1'
b111111111000000 &
b111111110000000 $
b111111110000000 B
b0 #
b0 >
0%
#1105000
b0 M
1O
1S
1%
#1110000
0%
#1115000
0W
b10000000000000 X
b11111111 T
1V
1Z
1%
#1120000
0%
#1125000
b111111111000000 !
b111111111000000 L
1"
1%
#1130000
0'
0%
#1135000
0S
1%
#1140000
0%
#1145000
0Z
1%
#1150000
0%
#1155000
0"
1%
#1160000
0%
#1165000
1%
#1170000
0%
#1175000
1%
#1180000
0%
#1185000
1%
#1190000
0%
#1195000
1%
#1200000
0%
#1205000
1%
#1210000
0%
#1215000
1%
#1220000
0%
#1225000
b1001 1
b10 )
b101 .
b11 *
1%
